loreme/__init__.py
loreme/check_gpu_availability.py
loreme/check_tags.py
loreme/dorado.py
loreme/download.py
loreme/env.py
loreme/export_bedgraph.py
loreme/gene_body_methylation.py
loreme/intersect.py
loreme/loreme.py
loreme/mean.py
loreme/merge.py
loreme/methylation_hist.py
loreme/modkit.py
loreme/parse_gff.py
loreme/pbcpg.py
loreme/plot.py
loreme/plot_bedtools.py
loreme/plot_genes.py
loreme/plot_repeats.py
loreme/promoter_methylation.py
loreme/version.py
loreme-0.2.4.dist-info/LICENSE
loreme-0.2.4.dist-info/METADATA
loreme-0.2.4.dist-info/WHEEL
loreme-0.2.4.dist-info/entry_points.txt
loreme-0.2.4.dist-info/top_level.txt
loreme-0.2.4.dist-info/RECORD
