Metadata-Version: 2.1
Name: loreme
Version: 0.2.4
Summary: Extract Methylation calls from ONT or PB long read data
Author-email: Anthony Aylward <aaylward@salk.edu>
Project-URL: Homepage, https://gitlab.com/salk-tm/loreme
Project-URL: Documentation, https://salk-tm.gitlab.io/loreme
Classifier: Programming Language :: Python :: 3
Classifier: Operating System :: OS Independent
Classifier: License :: OSI Approved :: MIT License
Requires-Python: >=3.7
License-File: LICENSE
Requires-Dist: urllib3
Requires-Dist: pybedtools
Requires-Dist: gff2bed
Requires-Dist: seaborn
Requires-Dist: pyfaidx
Requires-Dist: psutil
Requires-Dist: gputil
Requires-Dist: tabulate
Requires-Dist: nvsmi
Requires-Dist: pod5
